ciderpolarity/CIDER.py
ciderpolarity/__init__.py
ciderpolarity/create_embeddings.py
ciderpolarity/create_vader.py
ciderpolarity/load_polarities.py
ciderpolarity/run_bootstrapping.py
ciderpolarity/stopwords.py
ciderpolarity/suggest_seeds.py
ciderpolarity/utils_funcs.py
ciderpolarity-0.3.3.dist-info/LICENSE
ciderpolarity-0.3.3.dist-info/METADATA
ciderpolarity-0.3.3.dist-info/WHEEL
ciderpolarity-0.3.3.dist-info/RECORD
