Metadata-Version: 2.1
Name: ciderpolarity
Version: 0.3.3
Summary: 
Home-page: https://github.com/jcy204/ciderPolarity
Author: jcy204
Author-email: jcy204@exeter.ac.uk
Requires-Python: >=3.7,<3.13
Classifier: Programming Language :: Python :: 3
Classifier: Programming Language :: Python :: 3.7
Classifier: Programming Language :: Python :: 3.8
Classifier: Programming Language :: Python :: 3.9
Classifier: Programming Language :: Python :: 3.10
Classifier: Programming Language :: Python :: 3.11
Requires-Dist: gensim (>=4.1.0,<5.0.0)
Requires-Dist: numpy (>=1.22.0,<2.0.0)
Requires-Dist: pandas (>=1.4.0,<2.0.0)
Requires-Dist: scikit-learn (>=1.1.0,<2.0.0)
Requires-Dist: scipy (>=1.8.0,<2.0.0)
Requires-Dist: tqdm (>=4.55.0,<5.0.0)
Requires-Dist: vadersentiment (>=3.3.2,<4.0.0)
Project-URL: Repository, https://github.com/jcy204/ciderPolarity
